{"seats":
  [
    [
      {"seatType": "regular", "label": "1", "status": "unavailable"},
      {"seatType": "regular", "label": "2", "status": "available"}, 
      {"seatType": "spacer"},
      {"seatType": "regular", "label": "3", "status": "available"},
      {"seatType": "regular", "label": "4", "status": "available"}
    ],
    [
      {"seatType": "regular", "label": "1", "status": "available"},
      {"seatType": "accessible", "label": "2", "status": "available"},
      {"seatType": "spacer"}, 
      {"seatType": "accessible", "label": "3", "status": "available"},
      {"seatType": "regular", "label": "4", "status": "available"}
    ],
    [
      {"seatType": "regular", "label": "1", "status": "unavailable"},
      {"seatType": "regular", "label": "2", "status": "unavailable"},
      {"seatType": "spacer"},
      {"seatType": "regular", "label": "3", "status": "available"},
      {"seatType": "regular", "label": "4", "status": "available"}
    ],
    [
      {"seatType": "regular", "label": "1", "status": "available"},
      {"seatType": "regular", "label": "2", "status": "available"},
      {"seatType": "spacer"},
      {"seatType": "regular", "label": "3", "status": "available"},
      {"seatType": "regular", "label": "4", "status": "available"}
    ]
  ], 
    "naming": {
      "rows": ["A", "B", "C", "D"],
      "columns": ["0", "1", "2", "3", "4"] 
    }
}
